Flask_State-1.1.4.data/data/migrations/637920a840f7_.py
Flask_State-1.1.4.data/data/migrations/alembic.ini
Flask_State-1.1.4.data/data/migrations/b6b1ecfc9524_.py
Flask_State-1.1.4.data/data/migrations/env.py
Flask_State-1.1.4.data/data/migrations/script.py.mako
flask_state/__about__.py
flask_state/__init__.py
flask_state/migrate.py
flask_state/conf/__init__.py
flask_state/conf/config.py
flask_state/controller/__init__.py
flask_state/controller/interceptors.py
flask_state/controller/manager.py
flask_state/controller/response_methods.py
flask_state/dao/__init__.py
flask_state/dao/host_status.py
flask_state/exceptions/__init__.py
flask_state/exceptions/error_code.py
flask_state/exceptions/log_msg.py
flask_state/migrations/alembic.ini
flask_state/migrations/env.py
flask_state/migrations/script.py.mako
flask_state/migrations/versions/637920a840f7_.py
flask_state/migrations/versions/b6b1ecfc9524_.py
flask_state/models/__init__.py
flask_state/models/flask_state_host.py
flask_state/models/flask_state_io.py
flask_state/services/__init__.py
flask_state/services/host_status.py
flask_state/utils/__init__.py
flask_state/utils/auth.py
flask_state/utils/constants.py
flask_state/utils/cron.py
flask_state/utils/date.py
flask_state/utils/file_lock.py
flask_state/utils/format_conf.py
flask_state/utils/logger.py
Flask_State-1.1.4.dist-info/METADATA
Flask_State-1.1.4.dist-info/WHEEL
Flask_State-1.1.4.dist-info/top_level.txt
Flask_State-1.1.4.dist-info/RECORD
