Metadata-Version: 2.1
Name: Flask-State
Version: 1.1.4
Summary: Show local state to users through Echarts.
Home-page: https://github.com/yoobool/flask-state
Author: Yoobool
Author-email: yhl@uuchat.io
Maintainer: Yoobool
License: BSD-3-Clause
Project-URL: Code, https://github.com/yoobool/flask-state
Project-URL: Issue tracker, https://github.com/yoobool/flask-state/issues
Platform: UNKNOWN
Classifier: Development Status :: 5 - Production/Stable
Classifier: Environment :: Web Environment
Classifier: Intended Audience :: Developers
Classifier: License :: OSI Approved :: BSD License
Classifier: Operating System :: OS Independent
Classifier: Programming Language :: Python
Classifier: Topic :: Internet :: WWW/HTTP :: Dynamic Content
Requires-Python: >=3.5
Requires-Dist: Flask (>=1.0)
Requires-Dist: Flask-SQLAlchemy (>=1.0)
Requires-Dist: psutil (>=5.7.0)
Requires-Dist: alembic (>=1.4.3)
Provides-Extra: dev
Requires-Dist: black ; extra == 'dev'
Requires-Dist: codespell ; extra == 'dev'
Requires-Dist: flake8 ; extra == 'dev'
Requires-Dist: isort ; extra == 'dev'
Requires-Dist: pip-tools ; extra == 'dev'
Requires-Dist: pre-commit ; extra == 'dev'
Requires-Dist: setuptools ; extra == 'dev'
Requires-Dist: twine ; extra == 'dev'
Requires-Dist: wheel ; extra == 'dev'
Provides-Extra: full
Requires-Dist: redis ; extra == 'full'
Provides-Extra: test
Requires-Dist: pytest ; extra == 'test'
Requires-Dist: redis ; extra == 'test'
